mixturemapping_binning/__init__.py
mixturemapping_binning/binning.py
src/__init__.py
src/binning.py
src/distributions.py
src/utils.py
src/layers/__init__.py
src/layers/_mapping.py
src/layers/binyield.py
src/layers/covmatrix.py
src/layers/distribution.py
src/layers/disttrafo.py
src/layers/generalmapping.py
src/layers/gmrmapping.py
src/layers/linearmapping.py
src/layers/normalization.py
mixturemapping_binning-0.5.5.dist-info/METADATA
mixturemapping_binning-0.5.5.dist-info/WHEEL
mixturemapping_binning-0.5.5.dist-info/top_level.txt
mixturemapping_binning-0.5.5.dist-info/RECORD
