Metadata-Version: 2.1
Name: mixturemapping-binning
Version: 0.5.5
Summary: UNKNOWN
Home-page: https://vk.github.io/mixturemapping-doc/
License: UNKNOWN
Keywords: binning mixturemapping
Platform: UNKNOWN
Classifier: Operating System :: OS Independent
Classifier: Programming Language :: Python
Classifier: Programming Language :: Python :: 3.7
Classifier: Programming Language :: Python :: 3.8
Classifier: Programming Language :: Python :: 3.9
Classifier: Programming Language :: Python :: 3.10
Classifier: Programming Language :: Python :: 3 :: Only
Requires-Python: >=3.7
Requires-Dist: numpy
Requires-Dist: shapely
Requires-Dist: scikit-learn
